odoo/addons/stock_available_mrp/README.rst
odoo/addons/stock_available_mrp/__init__.py
odoo/addons/stock_available_mrp/__manifest__.py
odoo/addons/stock_available_mrp/demo/mrp_data.xml
odoo/addons/stock_available_mrp/i18n/de.po
odoo/addons/stock_available_mrp/i18n/es.po
odoo/addons/stock_available_mrp/i18n/fi.po
odoo/addons/stock_available_mrp/i18n/fr.po
odoo/addons/stock_available_mrp/i18n/hr_HR.po
odoo/addons/stock_available_mrp/i18n/it.po
odoo/addons/stock_available_mrp/i18n/pt_BR.po
odoo/addons/stock_available_mrp/i18n/sl.po
odoo/addons/stock_available_mrp/i18n/stock_available_mrp.pot
odoo/addons/stock_available_mrp/i18n/zh_CN.po
odoo/addons/stock_available_mrp/models/__init__.py
odoo/addons/stock_available_mrp/models/product_product.py
odoo/addons/stock_available_mrp/readme/CONTRIBUTORS.rst
odoo/addons/stock_available_mrp/readme/DESCRIPTION.rst
odoo/addons/stock_available_mrp/readme/ROADMAP.rst
odoo/addons/stock_available_mrp/static/description/icon.png
odoo/addons/stock_available_mrp/static/description/index.html
odoo/addons/stock_available_mrp/tests/__init__.py
odoo/addons/stock_available_mrp/tests/test_potential_qty.py
odoo12_addon_stock_available_mrp-12.0.1.0.2.dist-info/METADATA
odoo12_addon_stock_available_mrp-12.0.1.0.2.dist-info/WHEEL
odoo12_addon_stock_available_mrp-12.0.1.0.2.dist-info/top_level.txt
odoo12_addon_stock_available_mrp-12.0.1.0.2.dist-info/RECORD
